django_rating_stars-0.3.dist-info/DESCRIPTION.rst
django_rating_stars-0.3.dist-info/METADATA
django_rating_stars-0.3.dist-info/RECORD
django_rating_stars-0.3.dist-info/WHEEL
django_rating_stars-0.3.dist-info/metadata.json
django_rating_stars-0.3.dist-info/top_level.txt
rating_stars/__init__.py
rating_stars/admin.py
rating_stars/apps.py
rating_stars/forms.py
rating_stars/models.py
rating_stars/tests.py
rating_stars/urls.py
rating_stars/views.py
rating_stars/locale/en/LC_MESSAGES/django.po
rating_stars/locale/ru/LC_MESSAGES/django.mo
rating_stars/locale/ru/LC_MESSAGES/django.po
rating_stars/locale/uk/LC_MESSAGES/django.mo
rating_stars/locale/uk/LC_MESSAGES/django.po
rating_stars/migrations/0001_initial.py
rating_stars/migrations/__init__.py
rating_stars/static/rating_stars/css/rating.css
rating_stars/static/rating_stars/images/stars.svg
rating_stars/static/rating_stars/js/rating.js
rating_stars/templates/rating_stars/rating.html
rating_stars/templates/rating_stars/rating_wrapper.html
rating_stars/templatetags/__init__.py
rating_stars/templatetags/rating_tags.py
