Metadata-Version: 2.0
Name: django-rating-stars
Version: 0.3
Summary: UNKNOWN
Home-page: https://github.com/bergsoftplus/django-rating-stars
Author: SilmarillionUA
Author-email: UNKNOWN
License: UNKNOWN
Keywords: django rating stars
Platform: UNKNOWN
Classifier: Development Status :: 5 - Production/Stable
Classifier: Environment :: Web Environment
Classifier: Framework :: Django
Classifier: Intended Audience :: Developers
Classifier: License :: OSI Approved :: MIT License
Classifier: Operating System :: OS Independent
Classifier: Programming Language :: Python
Classifier: Programming Language :: Python :: 3
Classifier: Topic :: Utilities
Requires-Dist: django (>=1.10.0)
